AUTHORS
LICENSE
MANIFEST.in
README.rst
setup.py
ape/__init__.py
ape/_tasks.py
ape/main.py
ape.egg-info/PKG-INFO
ape.egg-info/SOURCES.txt
ape.egg-info/dependency_links.txt
ape.egg-info/not-zip-safe
ape.egg-info/requires.txt
ape.egg-info/top_level.txt
ape/container_mode/__init__.py
ape/container_mode/tasks.py
ape/installtools/__init__.py
ape/installtools/pool.py
ape/installtools/pypath.py
ape/installtools/venv.py
ape/resources/activape_template
ape/resources/aperun_template
ape/test/__init__.py
ape/test/argparser.py
ape/test/base.py
ape/test/invokation.py
ape/test/run.py
bin/ape
bin/bootstrape