Metadata-Version: 1.1
Name: ape
Version: 0.4.0
Summary: A Productive Environment - make/rake/ant/fab-like system with support for FOSD
Home-page: http://github.com/henzk/ape
Author: Hendrik Speidel
Author-email: hendrik@schnapptack.de
License: MIT License
Keywords: fosd,fop,features,build tool
Platform: UNKNOWN
Classifier: License :: OSI Approved :: MIT License
Classifier: Programming Language :: Python
Classifier: Intended Audience :: Developers
Classifier: Intended Audience :: System Administrators
Classifier: Operating System :: OS Independent
Classifier: Topic :: System :: Systems Administration
Classifier: Topic :: Software Development
Classifier: Topic :: Software Development :: Build Tools
Classifier: Topic :: Software Development :: Libraries
Classifier: Topic :: Software Development :: Libraries :: Python Modules
Classifier: Environment :: Console
